csvfiler/__init__.py
csvfiler/utils.py
csvfiler-0.1.1.dist-info/LICENSE
csvfiler-0.1.1.dist-info/METADATA
csvfiler-0.1.1.dist-info/WHEEL
csvfiler-0.1.1.dist-info/top_level.txt
csvfiler-0.1.1.dist-info/RECORD
